{"timestamp": "01150927", "num_seeds": 1, "task": "tsa-bin", "model_shortname": "NorBERT_3_base", "machinery": "fox", "args_dict": {"model_name_or_path": "ltg/norbert3-base", "dataset_name": "data/tsa_binary", "seed": 101, "per_device_train_batch_size": 64, "task_name": "01150927_tsa-bin_NorBERT_3_base", "output_dir": "/cluster/work/projects/ec30/egilron/tsa-hf/01150927_tsa-bin_NorBERT_3_base", "overwrite_cache": true, "overwrite_output_dir": true, "do_train": true, "num_train_epochs": 20, "do_eval": true, "return_entity_level_metrics": false, "use_auth_token": false, "logging_strategy": "epoch", "save_strategy": "epoch", "evaluation_strategy": "epoch", "save_total_limit": 1, "load_best_model_at_end": true, "label_column_name": "tsa_tags", "disable_tqdm": true, "do_predict": true, "text_column_name": "tokens", "learning_rate": 1e-06}, "best_epoch": 1, "train_epochs_val": [{"eval_loss": 1.4926880598068237, "eval_precision": 0.0, "eval_recall": 0.0, "eval_f1": 0.0, "eval_accuracy": 0.9341851308577164, "eval_runtime": 3.0275, "eval_samples_per_second": 505.698, "eval_steps_per_second": 63.419, "epoch": 1.0, "step": 135}, {"eval_loss": 1.3568943738937378, "eval_precision": 0.0, "eval_recall": 0.0, "eval_f1": 0.0, "eval_accuracy": 0.9341851308577164, "eval_runtime": 2.9882, "eval_samples_per_second": 512.354, "eval_steps_per_second": 64.253, "epoch": 2.0, "step": 270}, {"eval_loss": 1.2466591596603394, "eval_precision": 0.0, "eval_recall": 0.0, "eval_f1": 0.0, "eval_accuracy": 0.9341851308577164, "eval_runtime": 2.9992, "eval_samples_per_second": 510.476, "eval_steps_per_second": 64.018, "epoch": 3.0, "step": 405}, {"eval_loss": 1.1517466306686401, "eval_precision": 0.0, "eval_recall": 0.0, "eval_f1": 0.0, "eval_accuracy": 0.9341851308577164, "eval_runtime": 2.9994, "eval_samples_per_second": 510.443, "eval_steps_per_second": 64.014, "epoch": 4.0, "step": 540}, {"eval_loss": 1.0686818361282349, "eval_precision": 0.0, "eval_recall": 0.0, "eval_f1": 0.0, "eval_accuracy": 0.9341851308577164, "eval_runtime": 2.9993, "eval_samples_per_second": 510.46, "eval_steps_per_second": 64.016, "epoch": 5.0, "step": 675}, {"eval_loss": 0.9957486391067505, "eval_precision": 0.0, "eval_recall": 0.0, "eval_f1": 0.0, "eval_accuracy": 0.9341851308577164, "eval_runtime": 2.9876, "eval_samples_per_second": 512.456, "eval_steps_per_second": 64.266, "epoch": 6.0, "step": 810}, {"eval_loss": 0.9317953586578369, "eval_precision": 0.0, "eval_recall": 0.0, "eval_f1": 0.0, "eval_accuracy": 0.9341851308577164, "eval_runtime": 2.9884, "eval_samples_per_second": 512.318, "eval_steps_per_second": 64.249, "epoch": 7.0, "step": 945}, {"eval_loss": 0.8759154677391052, "eval_precision": 0.0, "eval_recall": 0.0, "eval_f1": 0.0, "eval_accuracy": 0.9341851308577164, "eval_runtime": 2.9932, "eval_samples_per_second": 511.497, "eval_steps_per_second": 64.146, "epoch": 8.0, "step": 1080}, {"eval_loss": 0.8273189067840576, "eval_precision": 0.0, "eval_recall": 0.0, "eval_f1": 0.0, "eval_accuracy": 0.9341851308577164, "eval_runtime": 2.9841, "eval_samples_per_second": 513.047, "eval_steps_per_second": 64.34, "epoch": 9.0, "step": 1215}, {"eval_loss": 0.7853054404258728, "eval_precision": 0.0, "eval_recall": 0.0, "eval_f1": 0.0, "eval_accuracy": 0.9341851308577164, "eval_runtime": 3.0626, "eval_samples_per_second": 499.895, "eval_steps_per_second": 62.691, "epoch": 10.0, "step": 1350}, {"eval_loss": 0.7492168545722961, "eval_precision": 0.0, "eval_recall": 0.0, "eval_f1": 0.0, "eval_accuracy": 0.9341851308577164, "eval_runtime": 2.9924, "eval_samples_per_second": 511.638, "eval_steps_per_second": 64.164, "epoch": 11.0, "step": 1485}, {"eval_loss": 0.7184697985649109, "eval_precision": 0.0, "eval_recall": 0.0, "eval_f1": 0.0, "eval_accuracy": 0.9341851308577164, "eval_runtime": 2.9921, "eval_samples_per_second": 511.675, "eval_steps_per_second": 64.168, "epoch": 12.0, "step": 1620}, {"eval_loss": 0.6925466060638428, "eval_precision": 0.0, "eval_recall": 0.0, "eval_f1": 0.0, "eval_accuracy": 0.9341851308577164, "eval_runtime": 2.9934, "eval_samples_per_second": 511.464, "eval_steps_per_second": 64.142, "epoch": 13.0, "step": 1755}, {"eval_loss": 0.670985996723175, "eval_precision": 0.0, "eval_recall": 0.0, "eval_f1": 0.0, "eval_accuracy": 0.9341851308577164, "eval_runtime": 2.9892, "eval_samples_per_second": 512.173, "eval_steps_per_second": 64.231, "epoch": 14.0, "step": 1890}, {"eval_loss": 0.6533942818641663, "eval_precision": 0.0, "eval_recall": 0.0, "eval_f1": 0.0, "eval_accuracy": 0.9341851308577164, "eval_runtime": 2.9821, "eval_samples_per_second": 513.397, "eval_steps_per_second": 64.384, "epoch": 15.0, "step": 2025}, {"eval_loss": 0.6394420266151428, "eval_precision": 0.0, "eval_recall": 0.0, "eval_f1": 0.0, "eval_accuracy": 0.9341851308577164, "eval_runtime": 2.9789, "eval_samples_per_second": 513.955, "eval_steps_per_second": 64.454, "epoch": 16.0, "step": 2160}, {"eval_loss": 0.6288632750511169, "eval_precision": 0.0, "eval_recall": 0.0, "eval_f1": 0.0, "eval_accuracy": 0.9341851308577164, "eval_runtime": 2.9878, "eval_samples_per_second": 512.425, "eval_steps_per_second": 64.262, "epoch": 17.0, "step": 2295}, {"eval_loss": 0.6214496493339539, "eval_precision": 0.0, "eval_recall": 0.0, "eval_f1": 0.0, "eval_accuracy": 0.9341851308577164, "eval_runtime": 2.9815, "eval_samples_per_second": 513.503, "eval_steps_per_second": 64.398, "epoch": 18.0, "step": 2430}, {"eval_loss": 0.6170551180839539, "eval_precision": 0.0, "eval_recall": 0.0, "eval_f1": 0.0, "eval_accuracy": 0.9341851308577164, "eval_runtime": 2.9906, "eval_samples_per_second": 511.931, "eval_steps_per_second": 64.2, "epoch": 19.0, "step": 2565}, {"eval_loss": 0.6155924797058105, "eval_precision": 0.0, "eval_recall": 0.0, "eval_f1": 0.0, "eval_accuracy": 0.9341851308577164, "eval_runtime": 3.0004, "eval_samples_per_second": 510.271, "eval_steps_per_second": 63.992, "epoch": 20.0, "step": 2700}]}