{"timestamp": "03121434", "num_seeds": 3, "task": "elsa-polarity", "model_shortname": "nb-bert-large", "machinery": "saga", "local_dataset": true, "args_dict": {"model_name_or_path": "NbAiLab/nb-bert-large", "dataset_name": "data/elsa-dataset_seqlabel", "seed": 303, "per_device_train_batch_size": 32, "task_name": "03121434_elsa-polarity_nb-bert-large", "output_dir": "/cluster/work/users/egilron/finetunes/03121434_elsa-polarity_nb-bert-large", "overwrite_cache": true, "overwrite_output_dir": true, "do_train": true, "num_train_epochs": 12, "do_eval": true, "return_entity_level_metrics": false, "use_auth_token": false, "logging_strategy": "epoch", "save_strategy": "epoch", "evaluation_strategy": "epoch", "save_total_limit": 1, "load_best_model_at_end": true, "label_column_name": "elsa_labels", "disable_tqdm": true, "report_to": null, "do_predict": true, "text_column_name": "tokens", "learning_rate": 5e-05, "trust_remote_code": false}, "best_epoch": 10, "train_epochs_val": [{"eval_loss": 0.06622108817100525, "eval_precision": 0.7304625199362041, "eval_recall": 0.7375201288244766, "eval_f1": 0.7339743589743589, "eval_accuracy": 0.988861531246336, "eval_runtime": 4.4977, "eval_samples_per_second": 336.395, "eval_steps_per_second": 42.244, "epoch": 10.0, "step": 2680}, {"eval_loss": 0.06084882840514183, "eval_precision": 0.721875, "eval_recall": 0.7439613526570048, "eval_f1": 0.732751784298176, "eval_accuracy": 0.9889396959393442, "eval_runtime": 4.4953, "eval_samples_per_second": 336.573, "eval_steps_per_second": 42.266, "epoch": 8.0, "step": 2144}, {"eval_loss": 0.06755930930376053, "eval_precision": 0.721259842519685, "eval_recall": 0.7375201288244766, "eval_f1": 0.7292993630573248, "eval_accuracy": 0.9887833665533279, "eval_runtime": 4.4867, "eval_samples_per_second": 337.221, "eval_steps_per_second": 42.348, "epoch": 11.0, "step": 2948}, {"eval_loss": 0.06565054506063461, "eval_precision": 0.7229299363057324, "eval_recall": 0.7310789049919485, "eval_f1": 0.7269815852682145, "eval_accuracy": 0.9887052018603197, "eval_runtime": 4.5284, "eval_samples_per_second": 334.112, "eval_steps_per_second": 41.957, "epoch": 9.0, "step": 2412}, {"eval_loss": 0.06784163415431976, "eval_precision": 0.7176656151419558, "eval_recall": 0.7326892109500805, "eval_f1": 0.7250996015936255, "eval_accuracy": 0.988822448899832, "eval_runtime": 4.5176, "eval_samples_per_second": 334.914, "eval_steps_per_second": 42.058, "epoch": 12.0, "step": 3216}, {"eval_loss": 0.051830194890499115, "eval_precision": 0.714968152866242, "eval_recall": 0.7230273752012882, "eval_f1": 0.7189751801441153, "eval_accuracy": 0.9883925430882871, "eval_runtime": 4.5292, "eval_samples_per_second": 334.058, "eval_steps_per_second": 41.95, "epoch": 5.0, "step": 1340}, {"eval_loss": 0.04908398538827896, "eval_precision": 0.6945288753799392, "eval_recall": 0.7359098228663447, "eval_f1": 0.7146207974980453, "eval_accuracy": 0.9885097901277993, "eval_runtime": 4.5532, "eval_samples_per_second": 332.295, "eval_steps_per_second": 41.729, "epoch": 4.0, "step": 1072}, {"eval_loss": 0.060327835381031036, "eval_precision": 0.707667731629393, "eval_recall": 0.7133655394524959, "eval_f1": 0.710505212510024, "eval_accuracy": 0.9883143783952788, "eval_runtime": 4.4894, "eval_samples_per_second": 337.012, "eval_steps_per_second": 42.321, "epoch": 6.0, "step": 1608}, {"eval_loss": 0.05831974372267723, "eval_precision": 0.6897637795275591, "eval_recall": 0.7053140096618358, "eval_f1": 0.697452229299363, "eval_accuracy": 0.9881971313557666, "eval_runtime": 4.5332, "eval_samples_per_second": 333.758, "eval_steps_per_second": 41.913, "epoch": 7.0, "step": 1876}, {"eval_loss": 0.039748117327690125, "eval_precision": 0.665680473372781, "eval_recall": 0.7246376811594203, "eval_f1": 0.6939090208172706, "eval_accuracy": 0.9880798843162544, "eval_runtime": 4.4948, "eval_samples_per_second": 336.613, "eval_steps_per_second": 42.271, "epoch": 2.0, "step": 536}, {"eval_loss": 0.04127633199095726, "eval_precision": 0.6367583212735166, "eval_recall": 0.7085346215780999, "eval_f1": 0.6707317073170732, "eval_accuracy": 0.9878453902372298, "eval_runtime": 4.4959, "eval_samples_per_second": 336.527, "eval_steps_per_second": 42.261, "epoch": 3.0, "step": 804}, {"eval_loss": 0.041023481637239456, "eval_precision": 0.6224489795918368, "eval_recall": 0.6876006441223832, "eval_f1": 0.6534047436878346, "eval_accuracy": 0.98698557861414, "eval_runtime": 4.8239, "eval_samples_per_second": 313.644, "eval_steps_per_second": 39.387, "epoch": 1.0, "step": 268}]}